<annotation>
	<folder>VOC2007</folder>
	<filename>001716.jpg</filename>
	<path>/Users/manlu/Desktop/VOC2007/001716.jpg</path>
	<source>
		<database>Unknown</database>
	</source>
	<size>
		<width>695</width>
		<height>1024</height>
		<depth>3</depth>
	</size>
	<segmented>0</segmented>
	<object>
		<name>fried egg</name>
		<pose>Unspecified</pose>
		<truncated>0</truncated>
		<difficult>0</difficult>
		<bndbox>
			<xmin>301</xmin>
			<ymin>657</ymin>
			<xmax>578</xmax>
			<ymax>838</ymax>
		</bndbox>
	</object>
	<object>
		<name>glass of milk</name>
		<pose>Unspecified</pose>
		<truncated>0</truncated>
		<difficult>0</difficult>
		<bndbox>
			<xmin>40</xmin>
			<ymin>136</ymin>
			<xmax>224</xmax>
			<ymax>406</ymax>
		</bndbox>
	</object>
	<object>
		<name>glass of milk</name>
		<pose>Unspecified</pose>
		<truncated>0</truncated>
		<difficult>0</difficult>
		<bndbox>
			<xmin>238</xmin>
			<ymin>34</ymin>
			<xmax>417</xmax>
			<ymax>347</ymax>
		</bndbox>
	</object>
</annotation>
