<annotation verified="yes">
	<folder>VOC2007</folder>
	<filename>002590.jpg</filename>
	<path>/Users/meishaonv/Desktop/VOC2007/002590.jpg</path>
	<source>
		<database>Unknown</database>
	</source>
	<size>
		<width>461</width>
		<height>371</height>
		<depth>3</depth>
	</size>
	<segmented>0</segmented>
	<object>
		<name>boiled potatoes</name>
		<pose>Unspecified</pose>
		<truncated>0</truncated>
		<difficult>0</difficult>
		<bndbox>
			<xmin>156</xmin>
			<ymin>74</ymin>
			<xmax>297</xmax>
			<ymax>170</ymax>
		</bndbox>
	</object>
	<object>
		<name>boiled potatoes</name>
		<pose>Unspecified</pose>
		<truncated>0</truncated>
		<difficult>0</difficult>
		<bndbox>
			<xmin>71</xmin>
			<ymin>99</ymin>
			<xmax>160</xmax>
			<ymax>188</ymax>
		</bndbox>
	</object>
	<object>
		<name>boiled potatoes</name>
		<pose>Unspecified</pose>
		<truncated>0</truncated>
		<difficult>0</difficult>
		<bndbox>
			<xmin>108</xmin>
			<ymin>154</ymin>
			<xmax>231</xmax>
			<ymax>221</ymax>
		</bndbox>
	</object>
	<object>
		<name>boiled potatoes</name>
		<pose>Unspecified</pose>
		<truncated>0</truncated>
		<difficult>0</difficult>
		<bndbox>
			<xmin>227</xmin>
			<ymin>150</ymin>
			<xmax>342</xmax>
			<ymax>220</ymax>
		</bndbox>
	</object>
	<object>
		<name>boiled potatoes</name>
		<pose>Unspecified</pose>
		<truncated>0</truncated>
		<difficult>0</difficult>
		<bndbox>
			<xmin>296</xmin>
			<ymin>107</ymin>
			<xmax>397</xmax>
			<ymax>204</ymax>
		</bndbox>
	</object>
	<object>
		<name>boiled potatoes</name>
		<pose>Unspecified</pose>
		<truncated>0</truncated>
		<difficult>0</difficult>
		<bndbox>
			<xmin>224</xmin>
			<ymin>42</ymin>
			<xmax>336</xmax>
			<ymax>140</ymax>
		</bndbox>
	</object>
</annotation>
