<annotation verified="yes">
	<folder>VOC2007</folder>
	<filename>002619.jpg</filename>
	<path>/Users/meishaonv/Desktop/VOC2007/002619.jpg</path>
	<source>
		<database>Unknown</database>
	</source>
	<size>
		<width>740</width>
		<height>555</height>
		<depth>3</depth>
	</size>
	<segmented>0</segmented>
	<object>
		<name>plain rice</name>
		<pose>Unspecified</pose>
		<truncated>0</truncated>
		<difficult>0</difficult>
		<bndbox>
			<xmin>458</xmin>
			<ymin>137</ymin>
			<xmax>724</xmax>
			<ymax>374</ymax>
		</bndbox>
	</object>
	<object>
		<name>plain rice</name>
		<pose>Unspecified</pose>
		<truncated>0</truncated>
		<difficult>0</difficult>
		<bndbox>
			<xmin>4</xmin>
			<ymin>8</ymin>
			<xmax>176</xmax>
			<ymax>169</ymax>
		</bndbox>
	</object>
</annotation>
