<annotation verified="yes">
	<folder>VOC2007</folder>
	<filename>003749.jpg</filename>
	<path>C:\Users\rober\Desktop\VOC2007\003749.jpg</path>
	<source>
		<database>Unknown</database>
	</source>
	<size>
		<width>1024</width>
		<height>683</height>
		<depth>3</depth>
	</size>
	<segmented>0</segmented>
	<object>
		<name>fried egg</name>
		<pose>Unspecified</pose>
		<truncated>0</truncated>
		<difficult>0</difficult>
		<bndbox>
			<xmin>273</xmin>
			<ymin>332</ymin>
			<xmax>686</xmax>
			<ymax>522</ymax>
		</bndbox>
	</object>
	<object>
		<name>fried egg</name>
		<pose>Unspecified</pose>
		<truncated>0</truncated>
		<difficult>0</difficult>
		<bndbox>
			<xmin>344</xmin>
			<ymin>155</ymin>
			<xmax>761</xmax>
			<ymax>346</ymax>
		</bndbox>
	</object>
</annotation>
