<annotation verified="yes">
	<folder>VOC2007</folder>
	<filename>004290.jpg</filename>
	<path>C:\Users\rober\Desktop\VOC2007\004290.jpg</path>
	<source>
		<database>Unknown</database>
	</source>
	<size>
		<width>750</width>
		<height>303</height>
		<depth>3</depth>
	</size>
	<segmented>0</segmented>
	<object>
		<name>chopped lettuce</name>
		<pose>Unspecified</pose>
		<truncated>0</truncated>
		<difficult>0</difficult>
		<bndbox>
			<xmin>11</xmin>
			<ymin>5</ymin>
			<xmax>733</xmax>
			<ymax>294</ymax>
		</bndbox>
	</object>
</annotation>
