<annotation>
	<folder>VOC2007</folder>
	<filename>004233.jpg</filename>
	<path>C:\Users\rober\Desktop\VOC2007\004233.jpg</path>
	<source>
		<database>Unknown</database>
	</source>
	<size>
		<width>300</width>
		<height>375</height>
		<depth>3</depth>
	</size>
	<segmented>0</segmented>
	<object>
		<name>plain rice</name>
		<pose>Unspecified</pose>
		<truncated>0</truncated>
		<difficult>0</difficult>
		<bndbox>
			<xmin>2</xmin>
			<ymin>123</ymin>
			<xmax>283</xmax>
			<ymax>287</ymax>
		</bndbox>
	</object>
</annotation>
