<annotation>
	<folder>VOC2007</folder>
	<filename>004753.jpg</filename>
	<path>C:\Users\rober\Desktop\VOC2007\004753.jpg</path>
	<source>
		<database>Unknown</database>
	</source>
	<size>
		<width>3456</width>
		<height>4676</height>
		<depth>3</depth>
	</size>
	<segmented>0</segmented>
	<object>
		<name>fried egg</name>
		<pose>Unspecified</pose>
		<truncated>0</truncated>
		<difficult>0</difficult>
		<bndbox>
			<xmin>718</xmin>
			<ymin>258</ymin>
			<xmax>1838</xmax>
			<ymax>1243</ymax>
		</bndbox>
	</object>
	<object>
		<name>fried egg</name>
		<pose>Unspecified</pose>
		<truncated>0</truncated>
		<difficult>0</difficult>
		<bndbox>
			<xmin>708</xmin>
			<ymin>1853</ymin>
			<xmax>1803</xmax>
			<ymax>2853</ymax>
		</bndbox>
	</object>
	<object>
		<name>fried egg</name>
		<pose>Unspecified</pose>
		<truncated>0</truncated>
		<difficult>0</difficult>
		<bndbox>
			<xmin>1768</xmin>
			<ymin>3233</ymin>
			<xmax>2968</xmax>
			<ymax>4283</ymax>
		</bndbox>
	</object>
	<object>
		<name>slice of bread</name>
		<pose>Unspecified</pose>
		<truncated>0</truncated>
		<difficult>0</difficult>
		<bndbox>
			<xmin>878</xmin>
			<ymin>3048</ymin>
			<xmax>1808</xmax>
			<ymax>4098</ymax>
		</bndbox>
	</object>
	<object>
		<name>slice of bread</name>
		<pose>Unspecified</pose>
		<truncated>0</truncated>
		<difficult>0</difficult>
		<bndbox>
			<xmin>2008</xmin>
			<ymin>1428</ymin>
			<xmax>2673</xmax>
			<ymax>2513</ymax>
		</bndbox>
	</object>
	<object>
		<name>slice of bread</name>
		<pose>Unspecified</pose>
		<truncated>0</truncated>
		<difficult>0</difficult>
		<bndbox>
			<xmin>2063</xmin>
			<ymin>303</ymin>
			<xmax>2408</xmax>
			<ymax>1103</ymax>
		</bndbox>
	</object>
	<object>
		<name>slice of bread</name>
		<pose>Unspecified</pose>
		<truncated>0</truncated>
		<difficult>0</difficult>
		<bndbox>
			<xmin>183</xmin>
			<ymin>873</ymin>
			<xmax>688</xmax>
			<ymax>1433</ymax>
		</bndbox>
	</object>
	<object>
		<name>slice of bread</name>
		<pose>Unspecified</pose>
		<truncated>1</truncated>
		<difficult>0</difficult>
		<bndbox>
			<xmin>1</xmin>
			<ymin>1526</ymin>
			<xmax>328</xmax>
			<ymax>2453</ymax>
		</bndbox>
	</object>
</annotation>
