<annotation verified="yes">
	<folder>VOC2007</folder>
	<filename>004767.jpg</filename>
	<path>C:\Users\rober\Desktop\VOC2007\004767.jpg</path>
	<source>
		<database>Unknown</database>
	</source>
	<size>
		<width>873</width>
		<height>1000</height>
		<depth>3</depth>
	</size>
	<segmented>0</segmented>
	<object>
		<name>chopped lettuce</name>
		<pose>Unspecified</pose>
		<truncated>0</truncated>
		<difficult>0</difficult>
		<bndbox>
			<xmin>157</xmin>
			<ymin>463</ymin>
			<xmax>344</xmax>
			<ymax>730</ymax>
		</bndbox>
	</object>
	<object>
		<name>glass of water</name>
		<pose>Unspecified</pose>
		<truncated>0</truncated>
		<difficult>0</difficult>
		<bndbox>
			<xmin>657</xmin>
			<ymin>125</ymin>
			<xmax>872</xmax>
			<ymax>467</ymax>
		</bndbox>
	</object>
	<object>
		<name>slice of bread</name>
		<pose>Unspecified</pose>
		<truncated>1</truncated>
		<difficult>0</difficult>
		<bndbox>
			<xmin>364</xmin>
			<ymin>61</ymin>
			<xmax>873</xmax>
			<ymax>285</ymax>
		</bndbox>
	</object>
</annotation>
