<annotation>
	<folder>VOC2007</folder>
	<filename>005017.jpg</filename>
	<path>/Users/manlu/Desktop/VOC2007/005017.jpg</path>
	<source>
		<database>Unknown</database>
	</source>
	<size>
		<width>2112</width>
		<height>2816</height>
		<depth>3</depth>
	</size>
	<segmented>0</segmented>
	<object>
		<name>glass of milk</name>
		<pose>Unspecified</pose>
		<truncated>0</truncated>
		<difficult>0</difficult>
		<bndbox>
			<xmin>789</xmin>
			<ymin>352</ymin>
			<xmax>1411</xmax>
			<ymax>2402</ymax>
		</bndbox>
	</object>
</annotation>
