<annotation>
	<folder>VOC2007</folder>
	<filename>005606.jpg</filename>
	<path>/Users/manlu/Desktop/VOC2007/005606.jpg</path>
	<source>
		<database>Unknown</database>
	</source>
	<size>
		<width>1080</width>
		<height>720</height>
		<depth>3</depth>
	</size>
	<segmented>0</segmented>
	<object>
		<name>fried egg</name>
		<pose>Unspecified</pose>
		<truncated>0</truncated>
		<difficult>0</difficult>
		<bndbox>
			<xmin>355</xmin>
			<ymin>265</ymin>
			<xmax>715</xmax>
			<ymax>470</ymax>
		</bndbox>
	</object>
	<object>
		<name>chopped lettuce</name>
		<pose>Unspecified</pose>
		<truncated>0</truncated>
		<difficult>0</difficult>
		<bndbox>
			<xmin>342</xmin>
			<ymin>549</ymin>
			<xmax>731</xmax>
			<ymax>654</ymax>
		</bndbox>
	</object>
</annotation>
