<annotation>
	<folder>VOC2007</folder>
	<filename>005869.jpg</filename>
	<path>/Users/manlu/Desktop/VOC2007/005869.jpg</path>
	<source>
		<database>Unknown</database>
	</source>
	<size>
		<width>283</width>
		<height>400</height>
		<depth>3</depth>
	</size>
	<segmented>0</segmented>
	<object>
		<name>glass of water</name>
		<pose>Unspecified</pose>
		<truncated>0</truncated>
		<difficult>0</difficult>
		<bndbox>
			<xmin>70</xmin>
			<ymin>77</ymin>
			<xmax>210</xmax>
			<ymax>336</ymax>
		</bndbox>
	</object>
</annotation>
