<annotation>
	<folder>VOC2007</folder>
	<filename>005926.jpg</filename>
	<path>/Users/manlu/Desktop/VOC2007/005926.jpg</path>
	<source>
		<database>Unknown</database>
	</source>
	<size>
		<width>0</width>
		<height>0</height>
		<depth>3</depth>
	</size>
	<segmented>0</segmented>
	<object>
		<name>glass of milk</name>
		<pose>Unspecified</pose>
		<truncated>0</truncated>
		<difficult>0</difficult>
		<bndbox>
			<xmin>89</xmin>
			<ymin>20</ymin>
			<xmax>220</xmax>
			<ymax>273</ymax>
		</bndbox>
	</object>
</annotation>
