<annotation>
	<folder>VOC2007</folder>
	<filename>005960.jpg</filename>
	<path>/Users/manlu/Desktop/VOC2007/005960.jpg</path>
	<source>
		<database>Unknown</database>
	</source>
	<size>
		<width>786</width>
		<height>1000</height>
		<depth>3</depth>
	</size>
	<segmented>0</segmented>
	<object>
		<name>chopped lettuce</name>
		<pose>Unspecified</pose>
		<truncated>0</truncated>
		<difficult>0</difficult>
		<bndbox>
			<xmin>161</xmin>
			<ymin>258</ymin>
			<xmax>469</xmax>
			<ymax>702</ymax>
		</bndbox>
	</object>
</annotation>
